MANIFEST.in
README.rst
setup.py
sphinx_opnfv_theme/__init__.py
sphinx_opnfv_theme/layout.html
sphinx_opnfv_theme/my_custom_sidebar.html
sphinx_opnfv_theme/relations.html
sphinx_opnfv_theme/theme.conf
sphinx_opnfv_theme.egg-info/PKG-INFO
sphinx_opnfv_theme.egg-info/SOURCES.txt
sphinx_opnfv_theme.egg-info/dependency_links.txt
sphinx_opnfv_theme.egg-info/entry_points.txt
sphinx_opnfv_theme.egg-info/requires.txt
sphinx_opnfv_theme.egg-info/top_level.txt
sphinx_opnfv_theme/static/favicon.ico
sphinx_opnfv_theme/static/logo.png
sphinx_opnfv_theme/static/my-styles.css