Metadata-Version: 1.0
Name: sphinx-opnfv-theme
Version: 0.2.0
Summary: OPNFV Theme for Sphinx
Home-page: https://docs.opnfv.org/
Author: Trevor Bramwell
Author-email: tbramwell@linuxfoundation.org
License: UNKNOWN
Platform: UNKNOWN
